tests/__init__.py
tests/test_cholesky.py
tests/test_factor.py
tests/test_helper.py
tests/test_ica.py
tests/test_lu.py
tests/test_nmf.py
tests/test_qr.py
tests/test_rec.py
tests/test_symrec.py
torchdecomp/__init__.py
torchdecomp/cholesky.py
torchdecomp/factor.py
torchdecomp/helper.py
torchdecomp/ica.py
torchdecomp/lu.py
torchdecomp/nmf.py
torchdecomp/qr.py
torchdecomp/rec.py
torchdecomp/symrec.py
torchdecomp-1.3.4.dist-info/LICENSE
torchdecomp-1.3.4.dist-info/METADATA
torchdecomp-1.3.4.dist-info/WHEEL
torchdecomp-1.3.4.dist-info/RECORD
