Metadata-Version: 2.1
Name: torchdecomp
Version: 1.3.4
Summary: A set of matrix decomposition algorithms implemented as PyTorch classes
Home-page: https://github.com/chiba-ai-med/PyTorchDecomp
License: MIT
Keywords: pytorch,machine learning
Author: Koki Tsuyuzaki
Author-email: k.t.the-answer@hotmail.co.jp
Maintainer: Koki Tsuyuzaki
Maintainer-email: k.t.the-answer@hotmail.co.jp
Requires-Python: >=3.10,<4.0
Classifier: Development Status :: 3 - Alpha
Classifier: Intended Audience :: Developers
Classifier: Intended Audience :: Education
Classifier: Intended Audience :: Science/Research
Classifier: License :: OSI Approved :: MIT License
Classifier: Natural Language :: English
Classifier: Operating System :: OS Independent
Classifier: Programming Language :: Python :: 3
Classifier: Programming Language :: Python :: 3.10
Classifier: Programming Language :: Python :: 3.11
Classifier: Programming Language :: Python :: 3
Classifier: Topic :: Scientific/Engineering
Classifier: Topic :: Scientific/Engineering :: Artificial Intelligence
Classifier: Topic :: Scientific/Engineering :: Mathematics
Classifier: Topic :: Software Development
Classifier: Topic :: Software Development :: Libraries
Classifier: Topic :: Software Development :: Libraries :: Python Modules
Requires-Dist: matplotlib (>=3.9.0,<4.0.0)
Requires-Dist: numpy (>=1.26.4,<2.0.0)
Requires-Dist: torch (>=2.3.1,<3.0.0)
Requires-Dist: torchvision (>=0.18.1,<0.19.0)
Project-URL: Repository, https://github.com/chiba-ai-med/PyTorchDecomp
